kapral/__init__.py
kapral/__main__.py
kapral/_version.py
kapral/corpus/__init__.py
kapral/corpus/base.py
kapral/corpus/corpus.py
kapral/corpus/iterators.py
kapral/corpus/preprocess.py
kapral/corpus/tokenization.py
kapral/utils/__init__.py
kapral/utils/data.py
kapral-0.1.3.dist-info/LICENSE
kapral-0.1.3.dist-info/METADATA
kapral-0.1.3.dist-info/WHEEL
kapral-0.1.3.dist-info/top_level.txt
kapral-0.1.3.dist-info/RECORD
