Metadata-Version: 2.1
Name: kapral
Version: 0.1.3
Summary: toolbox for various tasks in the area of corpus linguistic
Home-page: http://vecto.space
Author: 
Author-email: 
Maintainer: 
Maintainer-email: 
License: Apache License 2.0
Keywords: NLP,linguistics,language
Platform: UNKNOWN
Classifier: Development Status :: 3 - Alpha
Classifier: Environment :: Console
Classifier: Intended Audience :: Science/Research
Classifier: License :: OSI Approved :: Apache Software License
Classifier: Natural Language :: English
Classifier: Operating System :: POSIX
Classifier: Programming Language :: Python :: 3.7
Classifier: Programming Language :: Python :: 3.8
Classifier: Programming Language :: Python :: 3.9
Classifier: Programming Language :: Python :: 3 :: Only
Classifier: Topic :: Text Processing :: Linguistic
Requires-Python: >=3.7
License-File: LICENSE
Requires-Dist: nltk
Requires-Dist: numpy
Requires-Dist: progressbar2
Requires-Dist: system-query
Requires-Dist: tqdm
Requires-Dist: traitlets
Requires-Dist: zstandard
